TAxCore/__init__.py
TAxCore/taxcore.py
taxcore-0.1.4.dist-info/LICENSE.TXT
taxcore-0.1.4.dist-info/METADATA
taxcore-0.1.4.dist-info/WHEEL
taxcore-0.1.4.dist-info/top_level.txt
taxcore-0.1.4.dist-info/RECORD
