Metadata-Version: 2.1
Name: taxcore
Version: 0.1.4
Summary: A comprehensive technical analysis library for Python.
Home-page: https://github.com/YavuzAkbay/taxcorelib
Author: Yavuz
Author-email: akbay.yavuz@example.com
License: GPLv3
Classifier: Programming Language :: Python :: 3
Classifier: License :: OSI Approved :: GNU General Public License v3 (GPLv3)
Classifier: Operating System :: OS Independent
Requires-Python: >=3.6
License-File: LICENSE.TXT
Requires-Dist: numpy
Requires-Dist: pandas
